ltfqia/__init__.py
ltfqia/app/app.py
ltfqia/bonding_curve.py
ltfqia/cashflow.py
ltfqia/interest_rate.py
ltfqia/net_present_value.py
ltfqia/test/__init__.py
ltfqia/test/test_bonding_curve.py
ltfqia/test/test_qia.py
ltfqia/utils/holoviz_linked_brushing.py
ltfqia-0.1.4.dist-info/LICENSE
ltfqia-0.1.4.dist-info/METADATA
ltfqia-0.1.4.dist-info/WHEEL
ltfqia-0.1.4.dist-info/RECORD
